{
  "nodes": [
    {
      "id": 0,
      "pos": [
        0,
        0
      ]
    },
    {
      "id": 1,
      "pos": [
        151,
        0
      ]
    },
    {
      "id": 2,
      "pos": [
        316,
        101
      ]
    },
    {
      "id": 3,
      "pos": [
        306,
        122
      ]
    },
    {
      "id": 4,
      "pos": [
        0,
        137
      ]
    },
    {
      "id": 5,
      "pos": [
        0,
        284
      ]
    },
    {
      "id": 6,
      "pos": [
        105,
        318
      ]
    },
    {
      "id": 7,
      "pos": [
        139,
        307
      ]
    },
    {
      "id": 8,
      "pos": [
        200,
        271
      ]
    },
    {
      "id": 9,
      "pos": [
        652,
        96
      ]
    },
    {
      "id": 10,
      "pos": [
        744,
        187
      ]
    },
    {
      "id": 11,
      "pos": [
        545,
        263
      ]
    },
    {
      "id": 12,
      "pos": [
        551,
        299
      ]
    },
    {
      "id": 13,
      "pos": [
        414,
        315
      ]
    },
    {
      "id": 14,
      "pos": [
        374,
        350
      ]
    },
    {
      "id": 15,
      "pos": [
        417,
        387
      ]
    },
    {
      "id": 16,
      "pos": [
        558,
        375
      ]
    },
    {
      "id": 17,
      "pos": [
        668,
        423
      ]
    },
    {
      "id": 18,
      "pos": [
        661,
        470
      ]
    },
    {
      "id": 19,
      "pos": [
        550,
        485
      ]
    },
    {
      "id": 20,
      "pos": [
        437,
        437
      ]
    },
    {
      "id": 21,
      "pos": [
        0,
        402
      ]
    },
    {
      "id": 22,
      "pos": [
        735,
        0
      ]
    },
    {
      "id": 23,
      "pos": [
        990,
        0
      ]
    },
    {
      "id": 24,
      "pos": [
        778,
        414
      ]
    },
    {
      "id": 25,
      "pos": [
        158,
        272
      ]
    },
    {
      "id": 26,
      "pos": [
        184,
        300
      ]
    },
    {
      "id": 27,
      "pos": [
        156,
        294
      ]
    }
  ],
  "provinces": [
    {
      "id": 0,
      "name": "Bgcrmtt",
      "border": [
        4,
        0,
        1,
        2,
        3
      ],
      "terrain": "flat",
      "neighbours": [
        2,
        1
      ]
    },
    {
      "id": 1,
      "name": "Xivvjcui",
      "border": [
        1,
        22,
        9,
        2
      ],
      "terrain": "flat",
      "neighbours": [
        0,
        2
      ]
    },
    {
      "id": 2,
      "name": "Aqhlycs",
      "border": [
        3,
        2,
        9,
        10,
        11,
        12,
        13,
        8
      ],
      "terrain": "flat",
      "neighbours": [
        0,
        1
      ]
    }
  ]
}